pycounts_hr/.virtual_documents/Untitled.ipynb
pycounts_hr/Untitled.ipynb
pycounts_hr/__init__.py
pycounts_hr/plotting.py
pycounts_hr/pycounts_hr.py
pycounts_hr-0.1.0.dist-info/LICENSE
pycounts_hr-0.1.0.dist-info/WHEEL
pycounts_hr-0.1.0.dist-info/METADATA
pycounts_hr-0.1.0.dist-info/RECORD
