Metadata-Version: 2.1
Name: pycounts-hr
Version: 0.1.0
Summary: A package to count the number of words in a document
License: MIT
Author: Hatef Rahmani
Requires-Python: >=3.9,<4.0
Classifier: License :: OSI Approved :: MIT License
Classifier: Programming Language :: Python :: 3
Classifier: Programming Language :: Python :: 3.10
Classifier: Programming Language :: Python :: 3.9
Requires-Dist: matplotlib (>=3.5.1,<4.0.0)
